pydreamlo/__init__.py
pydreamlo/pydreamlo.py
pydreamlo-0.0.3.dist-info/LICENSE
pydreamlo-0.0.3.dist-info/METADATA
pydreamlo-0.0.3.dist-info/WHEEL
pydreamlo-0.0.3.dist-info/top_level.txt
pydreamlo-0.0.3.dist-info/RECORD
