Metadata-Version: 2.1
Name: pydreamlo
Version: 0.0.3
Summary: A free,simple and easy-to-use package to add leaderboard system to your games/apps.
Author: Goutham(cool-guy)
Project-URL: Homepage, https://github.com/cool-dev-guy/pydreamlo
Project-URL: Bug Tracker, https://github.com/cool-dev-guy/pydreamlo/issues
Classifier: Programming Language :: Python :: 3
Classifier: License :: OSI Approved :: MIT License
Classifier: Operating System :: OS Independent
Requires-Python: >=3.6
License-File: LICENSE
